ruleof40/__init__.py
ruleof40/ruleof40.py
ruleof40-0.0.2.dist-info/METADATA
ruleof40-0.0.2.dist-info/WHEEL
ruleof40-0.0.2.dist-info/top_level.txt
ruleof40-0.0.2.dist-info/RECORD
