Metadata-Version: 2.1
Name: ruleof40
Version: 0.0.2
Summary: Wrapper API for the ruleof40.trade webapp.  Returns the current and historic list of Rule of 40 stocks and includes scores and relevant dates etc.
Home-page: https://github.com/s-kerin/ruleof40
Author: Stephen Kerin
Author-email: skerin@gmail.com
License: UNKNOWN
Project-URL: Bug Tracker, https://github.com/s-kerin/ruleof40/issues
Platform: UNKNOWN
Classifier: Programming Language :: Python :: 3
Classifier: License :: OSI Approved :: MIT License
Classifier: Operating System :: OS Independent
Requires-Python: >=3.6
